simulation/__init__.py
simulation/constants.py
simulation/accuracy/__init__.py
simulation/accuracy/asymptotic.py
simulation/accuracy/constants.py
simulation/accuracy/save.py
simulation/model/__init__.py
simulation/model/cache.py
simulation/model/check_integrity.py
simulation/model/constants.py
simulation/model/data.py
simulation/model/eval.py
simulation/model/job.py
simulation/model/options.py
simulation/model/remove.py
simulation/model/save.py
simulation/model/update_convert_input_files_to_symlinks.py
simulation/model/update_data_base.py
simulation/model/update_job_options.py
simulation/oed/__init__.py
simulation/oed/constants.py
simulation/oed/cost_function.py
simulation/oed/main.py
simulation/optimization/__init__.py
simulation/optimization/constants.py
simulation/optimization/cost_function.py
simulation/optimization/job.py
simulation/optimization/min_values.py
simulation/optimization/results.py
simulation/optimization/save.py
simulation/optimization/matlab/__init__.py
simulation/optimization/matlab/constants.py
simulation/optimization/matlab/cost_function.py
simulation/plot/__init__.py
simulation/plot/average_model_confidence_increase.py
simulation/plot/interface.py
simulation/plot/model_confidence.py
simulation/plot/model_diff.py
simulation/plot/model_output.py
simulation/plot/optimization.py
simulation/plot/optimization_cost_functions.py
simulation/plot/optimization_parameters.py
simulation-0.1.1.dev80.dist-info/DESCRIPTION.rst
simulation-0.1.1.dev80.dist-info/METADATA
simulation-0.1.1.dev80.dist-info/RECORD
simulation-0.1.1.dev80.dist-info/WHEEL
simulation-0.1.1.dev80.dist-info/metadata.json
simulation-0.1.1.dev80.dist-info/top_level.txt
